annuvce/__init__.py
annuvce/functions.py
annuvce-0.1.0.dist-info/METADATA
annuvce-0.1.0.dist-info/WHEEL
annuvce-0.1.0.dist-info/top_level.txt
annuvce-0.1.0.dist-info/RECORD
